emojigg/__init__.py
emojigg/client.py
emojigg/emoji.py
emojigg/errors.py
emojigg/http.py
emojigg/pack.py
emojigg/utils.py
emojigg-0.1.5.1.dist-info/LICENSE
emojigg-0.1.5.1.dist-info/METADATA
emojigg-0.1.5.1.dist-info/WHEEL
emojigg-0.1.5.1.dist-info/entry_points.txt
emojigg-0.1.5.1.dist-info/top_level.txt
emojigg-0.1.5.1.dist-info/RECORD
