Metadata-Version: 2.1
Name: emojigg
Version: 0.1.5.1
Summary: Async wrapper for the EmojiGG api.
Home-page: https://github.com/NextChai/Emojigg
Author: Iced Chai
License: MIT
Project-URL: Documentation, https://github.com/NextChai/Emojigg/wiki
Project-URL: Report a Bug, https://github.com/NextChai/Emojigg/issues
Project-URL: Contribute, https://github.com/NextChai/Emojigg/pulls
Platform: UNKNOWN
Classifier: License :: OSI Approved :: MIT License
Classifier: Programming Language :: Python :: 3.6
Classifier: Programming Language :: Python :: 3.7
Classifier: Programming Language :: Python :: 3.8
Classifier: Programming Language :: Python :: 3.9
License-File: LICENSE
Requires-Dist: aiofiles (==0.7.0)
